[
  {
    "id": 1,
    "url": "https://www.astro21.cz/img/original/162/8-6-09-letiste-ruzyne-403.jpg",
    "alt": "letiště"
  },
  {
    "id": 2,
    "url": "https://www.astro21.cz/img/original/164/8-6-09-letiste-ruzyne-435.jpg",
    "alt": "letiště"
  },
  {
    "id": 3,
    "url": "https://www.astro21.cz/img/original/165/ruzyne-2009-115.jpg",
    "alt": "letiště"
  },
  {
    "id": 4,
    "url": "https://www.astro21.cz/img/original/193/025.jpg",
    "alt": "letiště"
  },
  {
    "id": 5,
    "url": "https://www.astro21.cz/img/original/196/082.jpg",
    "alt": "letiště"
  },
  {
    "id": 6,
    "url": "https://www.astro21.cz/img/original/197/084.jpg",
    "alt": "letiště"
  },
  {
    "id": 7,
    "url": "https://www.astro21.cz/img/original/198/189.jpg",
    "alt": "letiště"
  },
  {
    "id": 8,
    "url": "https://www.astro21.cz/img/original/199/199.jpg",
    "alt": "letiště"
  },
  {
    "id": 9,
    "url": "https://www.astro21.cz/img/original/200/213.jpg",
    "alt": "letiště"
  },
  {
    "id": 10,
    "url": "https://www.astro21.cz/img/original/201/222.jpg",
    "alt": "letiště"
  },
  {
    "id": 11,
    "url": "https://www.astro21.cz/img/original/204/235.jpg",
    "alt": "letiště"
  }
]